pyavd_cli/__init__.py
pyavd_cli/build.py
pyavd_cli-0.2.1.dist-info/METADATA
pyavd_cli-0.2.1.dist-info/WHEEL
pyavd_cli-0.2.1.dist-info/entry_points.txt
pyavd_cli-0.2.1.dist-info/licenses/LICENSE
pyavd_cli-0.2.1.dist-info/RECORD
