Metadata-Version: 2.4
Name: pyavd-cli
Version: 0.2.1
Summary: A collection of cli scripts to use pyavd
License-File: LICENSE
Author: Arista Networks
Author-email: ps-sw-dev-team@arista.com
Requires-Python: >=3.11,<4
Classifier: Programming Language :: Python :: 3
Classifier: Programming Language :: Python :: 3.11
Classifier: Programming Language :: Python :: 3.12
Classifier: Programming Language :: Python :: 3.13
Classifier: Programming Language :: Python :: 3.14
Provides-Extra: dev
Requires-Dist: build (>=1.3.0,<1.4.0) ; extra == "dev"
Requires-Dist: mypy (>=1.19.1,<1.20.0) ; extra == "dev"
Requires-Dist: pre-commit (>=4.5.1,<4.6.0) ; extra == "dev"
Requires-Dist: pyavd[ansible] (>=5.3,<6.0)
Requires-Dist: ruff (>=0.14.9,<0.15.0) ; extra == "dev"
Requires-Dist: types-pyyaml (>=6.0.12.20250915,<6.1.0.0) ; extra == "dev"
